midir/__init__.py
midir-1.2.0.dist-info/licenses/LICENSE
midir-1.2.0.dist-info/METADATA
midir-1.2.0.dist-info/WHEEL
midir-1.2.0.dist-info/top_level.txt
midir-1.2.0.dist-info/RECORD
