Metadata-Version: 2.4
Name: midir
Version: 1.2.0
Summary: midir is a Python library designed to handle relative module dependencies by 
Author-email: Jordi Carrera Ventura <jordi.carrera.ventura@gmail.com>
Project-URL: Google page, https://www.google.com
Classifier: Programming Language :: Python :: 3
Classifier: Operating System :: OS Independent
Requires-Python: >=3.9
License-File: LICENSE
Requires-Dist: build
Requires-Dist: pytest
Requires-Dist: twine
Dynamic: license-file
